ascid/__init__.py
ascid/__main__.py
ascid/ascid.py
ascid/pyrstrmax.py
ascid-0.2.0.dist-info/LICENSE
ascid-0.2.0.dist-info/METADATA
ascid-0.2.0.dist-info/WHEEL
ascid-0.2.0.dist-info/entry_points.txt
ascid-0.2.0.dist-info/top_level.txt
ascid-0.2.0.dist-info/RECORD
